<objects>
    <!-- 魔階トチョウ（偽） 南 floor05 -->
    <object name="ServerZone">
        <member name="ID">1300125</member>
        <member name="DynamicMapID">13001025</member>
        <member name="Global">true</member>
        <member name="StartingX">0</member>
        <member name="StartingY">0</member>
        <member name="StartingRotation">0</member>
        <member name="NPCs">
            <element>
                <object name="ServerNPC">
                    <member name="ID">2367</member>
                    <member name="X">2313.55</member>
                    <member name="Y">56.429</member>
                    <member name="Rotation">-1.57</member>
                    <member name="Actions"/>
                </object>
            </element>
            <element>
                <object name="ServerNPC">
                    <member name="ID">2367</member>
                    <member name="X">349.788</member>
                    <member name="Y">8113.69</member>
                    <member name="Rotation">-1.57</member>
                    <member name="Actions"/>
                </object>
            </element>
            <element>
                <!-- アスタロト -->
                <object name="ServerNPC">
                    <member name="ID">3550</member>
                    <member name="X">2310.32</member>
                    <member name="Y">5309.65</member>
                    <member name="Rotation">-1.57</member>
                    <member name="Actions">
                        <element>
                            <object name="ActionStartEvent">
                                <member name="eventID">Z1300125_NM001</member>
                            </object>
                        </element>
                    </member>
                </object>
            </element>
            <element>
                <!-- ※デバッグ用NPC -->
                <object name="ServerNPC">
                    <member name="ID">99035</member>
                    <member name="X">376.148</member>
                    <member name="Y">-336.51</member>
                    <member name="Rotation">3.14</member>
                    <member name="Actions"/>
                </object>
            </element>
            <element>
                <!-- ※デバッグ用NPC -->
                <object name="ServerNPC">
                    <member name="ID">99035</member>
                    <member name="X">2615.03</member>
                    <member name="Y">5320.88</member>
                    <member name="Rotation">-1.57</member>
                    <member name="Actions"/>
                </object>
            </element>
        </member>
        <member name="Objects">
            <element>
                <!-- 扉 -->
                <object name="ServerObject">
                    <member name="ID">660034</member>
                    <member name="X">796.688</member>
                    <member name="Y">5.5328</member>
                    <member name="Rotation">0</member>
                    <member name="Actions"/>
                    <member name="State">2</member>
                </object>
            </element>
            <element>
                <!-- 扉 -->
                <object name="ServerObject">
                    <member name="ID">660035</member>
                    <member name="X">1377.08</member>
                    <member name="Y">-3.43847</member>
                    <member name="Rotation">0</member>
                    <member name="Actions"/>
                    <member name="State">2</member>
                </object>
            </element>
            <element>
                <!-- 扉 -->
                <object name="ServerObject">
                    <member name="ID">660036</member>
                    <member name="X">2310.69</member>
                    <member name="Y">773.95</member>
                    <member name="Rotation">-1.5708</member>
                    <member name="Actions"/>
                    <member name="State">2</member>
                </object>
            </element>
            <element>
                <!-- 扉 -->
                <object name="ServerObject">
                    <member name="ID">660037</member>
                    <member name="X">2303.17</member>
                    <member name="Y">3847.07</member>
                    <member name="Rotation">-1.5708</member>
                    <member name="Actions"/>
                    <member name="State">2</member>
                </object>
            </element>
            <element>
                <!-- 扉 -->
                <object name="ServerObject">
                    <member name="ID">660038</member>
                    <member name="X">2310.34</member>
                    <member name="Y">6926.95</member>
                    <member name="Rotation">-1.5708</member>
                    <member name="Actions"/>
                    <member name="State">2</member>
                </object>
            </element>
            <element>
                <!-- 扉 -->
                <object name="ServerObject">
                    <member name="ID">660039</member>
                    <member name="X">1169.58</member>
                    <member name="Y">8105.82</member>
                    <member name="Rotation">0</member>
                    <member name="Actions"/>
                    <member name="State">2</member>
                </object>
            </element>
            <element>
                <!-- 扉 -->
                <object name="ServerObject">
                    <member name="ID">660040</member>
                    <member name="X">373.123</member>
                    <member name="Y">8872.17</member>
                    <member name="Rotation">-1.5708</member>
                    <member name="Actions"/>
                    <member name="State">2</member>
                </object>
            </element>
            <element>
                <!-- 扉 -->
                <object name="ServerObject">
                    <member name="ID">660041</member>
                    <member name="X">1500.81</member>
                    <member name="Y">10005</member>
                    <member name="Rotation">3.14159</member>
                    <member name="Actions"/>
                    <member name="State">2</member>
                </object>
            </element>
            <element>
                <!-- 扉 -->
                <object name="ServerObject">
                    <member name="ID">660042</member>
                    <member name="X">2459.47</member>
                    <member name="Y">10793.6</member>
                    <member name="Rotation">-1.5708</member>
                    <member name="Actions"/>
                    <member name="State">2</member>
                </object>
            </element>
            <element>
                <!-- 扉 -->
                <object name="ServerObject">
                    <member name="ID">660043</member>
                    <member name="X">2461.8</member>
                    <member name="Y">11362.7</member>
                    <member name="Rotation">-1.5708</member>
                    <member name="Actions"/>
                    <member name="State">2</member>
                </object>
            </element>
            <element>
                <!-- 間欠泉 -->
                <object name="ServerObject">
                    <member name="ID">661009</member>
                    <member name="X">-335.817</member>
                    <member name="Y">9.15082</member>
                    <member name="Rotation">0</member>
                    <member name="Actions"/>
                    <member name="State">2</member>
                </object>
            </element>
            <element>
                <!-- 間欠泉 -->
                <object name="ServerObject">
                    <member name="ID">661010</member>
                    <member name="X">2448.35</member>
                    <member name="Y">12494.3</member>
                    <member name="Rotation">-1.5708</member>
                    <member name="Actions"/>
                    <member name="State">2</member>
                </object>
            </element>
        </member>
        <member name="Spawns">
            <pair>
                <key>567000001</key>
                <value>
                    <object name="Spawn">
                        <member name="ID">567000001</member>
                        <member name="EnemyType">5670</member>
                        <member name="Drops"/>
                    </object>
                </value>
            </pair>
            <pair>
                <key>567500001</key>
                <value>
                    <object name="Spawn">
                        <member name="ID">567500001</member>
                        <member name="EnemyType">5675</member>
                        <member name="Drops">
                            <element>
                                <object name="ItemDrop">
                                    <member name="ItemType">38222</member>
                                    <member name="Rate">0.05000000075</member>
                                    <member name="MinStack">1</member>
                                    <member name="MaxStack">1</member>
                                </object>
                            </element>
                            <element>
                                <object name="ItemDrop">
                                    <member name="ItemType">5051</member>
                                    <member name="Rate">0.05000000075</member>
                                    <member name="MinStack">1</member>
                                    <member name="MaxStack">1</member>
                                </object>
                            </element>
                        </member>
                    </object>
                </value>
            </pair>
            <pair>
                <key>567600001</key>
                <value>
                    <object name="Spawn">
                        <member name="ID">567600001</member>
                        <member name="EnemyType">5676</member>
                        <member name="Drops">
                            <element>
                                <object name="ItemDrop">
                                    <member name="ItemType">5052</member>
                                    <member name="Rate">0.05000000075</member>
                                    <member name="MinStack">1</member>
                                    <member name="MaxStack">1</member>
                                </object>
                            </element>
                        </member>
                    </object>
                </value>
            </pair>
            <pair>
                <key>567700001</key>
                <value>
                    <object name="Spawn">
                        <member name="ID">567700001</member>
                        <member name="EnemyType">5677</member>
                        <member name="Drops">
                            <element>
                                <object name="ItemDrop">
                                    <member name="ItemType">704</member>
                                    <member name="Rate">0.05000000075</member>
                                    <member name="MinStack">1</member>
                                    <member name="MaxStack">1</member>
                                </object>
                            </element>
                        </member>
                    </object>
                </value>
            </pair>
            <pair>
                <key>567800001</key>
                <value>
                    <object name="Spawn">
                        <member name="ID">567800001</member>
                        <member name="EnemyType">5678</member>
                        <member name="Drops"/>
                    </object>
                </value>
            </pair>
            <pair>
                <key>568300001</key>
                <value>
                    <object name="Spawn">
                        <member name="ID">568300001</member>
                        <member name="EnemyType">5683</member>
                        <member name="Drops">
                            <element>
                                <object name="ItemDrop">
                                    <member name="ItemType">38224</member>
                                    <member name="Rate">0.05000000075</member>
                                    <member name="MinStack">1</member>
                                    <member name="MaxStack">1</member>
                                </object>
                            </element>
                        </member>
                    </object>
                </value>
            </pair>
            <pair>
                <key>568400001</key>
                <value>
                    <object name="Spawn">
                        <member name="ID">568400001</member>
                        <member name="EnemyType">5684</member>
                        <member name="Drops">
                            <element>
                                <object name="ItemDrop">
                                    <member name="ItemType">5056</member>
                                    <member name="Rate">0.05000000075</member>
                                    <member name="MinStack">1</member>
                                    <member name="MaxStack">1</member>
                                </object>
                            </element>
                            <element>
                                <object name="ItemDrop">
                                    <member name="ItemType">38224</member>
                                    <member name="Rate">0.05000000075</member>
                                    <member name="MinStack">1</member>
                                    <member name="MaxStack">1</member>
                                </object>
                            </element>
                        </member>
                    </object>
                </value>
            </pair>
            <pair>
                <key>568500001</key>
                <value>
                    <object name="Spawn">
                        <member name="ID">568500001</member>
                        <member name="EnemyType">5685</member>
                        <member name="Drops">
                            <element>
                                <object name="ItemDrop">
                                    <member name="ItemType">38224</member>
                                    <member name="Rate">0.05000000075</member>
                                    <member name="MinStack">1</member>
                                    <member name="MaxStack">1</member>
                                </object>
                            </element>
                        </member>
                    </object>
                </value>
            </pair>
            <pair>
                <key>568600001</key>
                <value>
                    <object name="Spawn">
                        <member name="ID">568600001</member>
                        <member name="EnemyType">5686</member>
                        <member name="Drops">
                            <element>
                                <object name="ItemDrop">
                                    <member name="ItemType">38224</member>
                                    <member name="Rate">0.05000000075</member>
                                    <member name="MinStack">1</member>
                                    <member name="MaxStack">1</member>
                                </object>
                            </element>
                        </member>
                    </object>
                </value>
            </pair>
        </member>
        <member name="SpawnGroups">
            <pair>
                <key>5670001</key>
                <value>
                    <object name="SpawnGroup">
                        <member name="ID">5670001</member>
                        <member name="SpawnID">567000001</member>
                        <member name="SpawnLocationGroupID">5670001</member>
                        <member name="MaxCount">5</member>
                        <member name="RespawnTime">5</member>
                    </object>
                </value>
            </pair>
            <pair>
                <key>5675001</key>
                <value>
                    <object name="SpawnGroup">
                        <member name="ID">5675001</member>
                        <member name="SpawnID">567500001</member>
                        <member name="SpawnLocationGroupID">5675001</member>
                        <member name="MaxCount">2</member>
                        <member name="RespawnTime">5</member>
                    </object>
                </value>
            </pair>
            <pair>
                <key>5676000</key>
                <value>
                    <object name="SpawnGroup">
                        <member name="ID">5676000</member>
                        <member name="SpawnID">567600001</member>
                        <member name="SpawnLocationGroupID">5676000</member>
                        <member name="MaxCount">2</member>
                        <member name="RespawnTime">5</member>
                    </object>
                </value>
            </pair>
            <pair>
                <key>5676001</key>
                <value>
                    <object name="SpawnGroup">
                        <member name="ID">5676001</member>
                        <member name="SpawnID">567600001</member>
                        <member name="SpawnLocationGroupID">5676001</member>
                        <member name="MaxCount">2</member>
                        <member name="RespawnTime">5</member>
                    </object>
                </value>
            </pair>
            <pair>
                <key>5677000</key>
                <value>
                    <object name="SpawnGroup">
                        <member name="ID">5677000</member>
                        <member name="SpawnID">567700001</member>
                        <member name="SpawnLocationGroupID">5677000</member>
                        <member name="MaxCount">2</member>
                        <member name="RespawnTime">5</member>
                    </object>
                </value>
            </pair>
            <pair>
                <key>5677001</key>
                <value>
                    <object name="SpawnGroup">
                        <member name="ID">5677001</member>
                        <member name="SpawnID">567700001</member>
                        <member name="SpawnLocationGroupID">5677001</member>
                        <member name="MaxCount">2</member>
                        <member name="RespawnTime">5</member>
                    </object>
                </value>
            </pair>
            <pair>
                <key>5678001</key>
                <value>
                    <object name="SpawnGroup">
                        <member name="ID">5678001</member>
                        <member name="SpawnID">567800001</member>
                        <member name="SpawnLocationGroupID">5678001</member>
                        <member name="MaxCount">2</member>
                        <member name="RespawnTime">5</member>
                    </object>
                </value>
            </pair>
            <pair>
                <key>5683001</key>
                <value>
                    <object name="SpawnGroup">
                        <member name="ID">5683001</member>
                        <member name="SpawnID">568300001</member>
                        <member name="SpawnLocationGroupID">5683001</member>
                        <member name="MaxCount">1</member>
                        <member name="RespawnTime">5</member>
                    </object>
                </value>
            </pair>
            <pair>
                <key>5684001</key>
                <value>
                    <object name="SpawnGroup">
                        <member name="ID">5684001</member>
                        <member name="SpawnID">568400001</member>
                        <member name="SpawnLocationGroupID">5684001</member>
                        <member name="MaxCount">1</member>
                        <member name="RespawnTime">5</member>
                    </object>
                </value>
            </pair>
            <pair>
                <key>5685001</key>
                <value>
                    <object name="SpawnGroup">
                        <member name="ID">5685001</member>
                        <member name="SpawnID">568500001</member>
                        <member name="SpawnLocationGroupID">5685001</member>
                        <member name="MaxCount">1</member>
                        <member name="RespawnTime">5</member>
                    </object>
                </value>
            </pair>
            <pair>
                <key>5686001</key>
                <value>
                    <object name="SpawnGroup">
                        <member name="ID">5686001</member>
                        <member name="SpawnID">568600001</member>
                        <member name="SpawnLocationGroupID">5686001</member>
                        <member name="MaxCount">1</member>
                        <member name="RespawnTime">5</member>
                    </object>
                </value>
            </pair>
        </member>
        <member name="SpawnLocationGroups">
            <pair>
                <key>5670001</key>
                <value>
                    <object name="SpawnLocationGroup">
                        <member name="ID">5670001</member>
                        <member name="SpotIDs">
                            <element>1003</element>
                            <element>2001</element>
                        </member>
                    </object>
                </value>
            </pair>
            <pair>
                <key>5675001</key>
                <value>
                    <object name="SpawnLocationGroup">
                        <member name="ID">5675001</member>
                        <member name="SpotIDs">
                            <element>1001</element>
                            <element>1002</element>
                        </member>
                    </object>
                </value>
            </pair>
            <pair>
                <key>5676000</key>
                <value>
                    <object name="SpawnLocationGroup">
                        <member name="ID">5676000</member>
                        <!-- Unknown -->
                    </object>
                </value>
            </pair>
            <pair>
                <key>5676001</key>
                <value>
                    <object name="SpawnLocationGroup">
                        <member name="ID">5676001</member>
                        <member name="SpotIDs">
                            <element>1001</element>
                            <element>1002</element>
                        </member>
                    </object>
                </value>
            </pair>
            <pair>
                <key>5677000</key>
                <value>
                    <object name="SpawnLocationGroup">
                        <member name="ID">5677000</member>
                        <!-- Unknown -->
                    </object>
                </value>
            </pair>
            <pair>
                <key>5677001</key>
                <value>
                    <object name="SpawnLocationGroup">
                        <member name="ID">5677001</member>
                        <member name="SpotIDs">
                            <element>1001</element>
                            <element>1002</element>
                        </member>
                    </object>
                </value>
            </pair>
            <pair>
                <key>5678001</key>
                <value>
                    <object name="SpawnLocationGroup">
                        <member name="ID">5678001</member>
                        <member name="SpotIDs">
                            <element>1001</element>
                            <element>1002</element>
                        </member>
                    </object>
                </value>
            </pair>
            <pair>
                <key>5683001</key>
                <value>
                    <object name="SpawnLocationGroup">
                        <member name="ID">5683001</member>
                        <member name="SpotIDs">
                            <element>1002</element>
                        </member>
                    </object>
                </value>
            </pair>
            <pair>
                <key>5684001</key>
                <value>
                    <object name="SpawnLocationGroup">
                        <member name="ID">5684001</member>
                        <member name="SpotIDs">
                            <element>1002</element>
                        </member>
                    </object>
                </value>
            </pair>
            <pair>
                <key>5685001</key>
                <value>
                    <object name="SpawnLocationGroup">
                        <member name="ID">5685001</member>
                        <member name="SpotIDs">
                            <element>1002</element>
                        </member>
                    </object>
                </value>
            </pair>
            <pair>
                <key>5686001</key>
                <value>
                    <object name="SpawnLocationGroup">
                        <member name="ID">5686001</member>
                        <member name="SpotIDs">
                            <element>1002</element>
                        </member>
                    </object>
                </value>
            </pair>
        </member>
        <member name="Spots"/>
    </object>
</objects>