<objects>
    <object name="ServerZone">
        <member name="ID">620102</member>
        <member name="DynamicMapID">6202002</member>
        <member name="Global">false</member>
        <member name="GroupID">90104</member>
        <member name="StartingX">432.10</member>
        <member name="StartingY">21.43</member>
        <member name="StartingRotation">-3.14</member>
        <member name="NPCs"/>
        <member name="Objects">
            <element>
                <object name="ServerObject">
                    <member name="ID">620021</member>
                    <member name="X">2492.611816</member>
                    <member name="Y">-9535.753906</member>
                    <member name="Rotation">-1.570796371</member>
                    <member name="State">0</member>
                    <member name="Actions"/>
                </object>
            </element>
            <element>
                <object name="ServerObject">
                    <member name="ID">620022</member>
                    <member name="ActorID">620022</member>
                    <member name="X">-483.502655</member>
                    <member name="Y">-6442.794434</member>
                    <member name="Rotation">1.570796371</member>
                    <member name="State">1</member>
                    <member name="Actions"/>
                </object>
            </element>
            <element>
                <object name="ServerObject">
                    <member name="ID">620023</member>
                    <member name="X">-479.2344055</member>
                    <member name="Y">-9444.298828</member>
                    <member name="Rotation">1.570796371</member>
                    <member name="State">0</member>
                    <member name="Actions"/>
                </object>
            </element>
            <element>
                <object name="ServerObject">
                    <member name="ID">620024</member>
                    <member name="X">931.7330322</member>
                    <member name="Y">-11009.43848</member>
                    <member name="Rotation">-3.141592741</member>
                    <member name="State">0</member>
                    <member name="Actions"/>
                </object>
            </element>
            <element>
                <object name="ServerObject">
                    <member name="ID">620025</member>
                    <member name="X">8480.760742</member>
                    <member name="Y">-9554.124023</member>
                    <member name="Rotation">-1.570796371</member>
                    <member name="State">0</member>
                    <member name="Actions"/>
                </object>
            </element>
            <element>
                <object name="ServerObject">
                    <member name="ID">620026</member>
                    <member name="X">3963.101318</member>
                    <member name="Y">-7987.350586</member>
                    <member name="Rotation">-3.141592741</member>
                    <member name="State">0</member>
                    <member name="Actions"/>
                </object>
            </element>
            <element>
                <object name="ServerObject">
                    <member name="ID">620027</member>
                    <member name="X">5516.144043</member>
                    <member name="Y">-9437.860352</member>
                    <member name="Rotation">1.570796371</member>
                    <member name="State">0</member>
                    <member name="Actions"/>
                </object>
            </element>
            <element>
                <object name="ServerObject">
                    <member name="ID">620028</member>
                    <member name="X">6938.251465</member>
                    <member name="Y">-10960.29297</member>
                    <member name="Rotation">-3.141592741</member>
                    <member name="State">0</member>
                    <member name="Actions"/>
                </object>
            </element>
            <element>
                <object name="ServerObject">
                    <member name="ID">620029</member>
                    <member name="ActorID">620029</member>
                    <member name="X">-1425.438599</member>
                    <member name="Y">-8.356666565</member>
                    <member name="Rotation">-0</member>
                    <member name="State">1</member>
                    <member name="Actions"/>
                </object>
            </element>
            <element>
                <object name="ServerObject">
                    <member name="ID">620030</member>
                    <member name="ActorID">620030</member>
                    <member name="X">16061.66113</member>
                    <member name="Y">485.9765015</member>
                    <member name="Rotation">-0</member>
                    <member name="State">1</member>
                    <member name="Actions"/>
                </object>
            </element>
            <element>
                <object name="ServerObject">
                    <member name="ID">620031</member>
                    <member name="ActorID">620031</member>
                    <member name="X">17436.46094</member>
                    <member name="Y">-10490.44922</member>
                    <member name="Rotation">-3.141592741</member>
                    <member name="State">1</member>
                    <member name="Actions"/>
                </object>
            </element>
            <element>
                <object name="ServerObject">
                    <member name="ID">620032</member>
                    <member name="X">19004.85352</member>
                    <member name="Y">-6069.555176</member>
                    <member name="Rotation">-1.570796371</member>
                    <member name="State">1</member>
                    <member name="Actions"/>
                </object>
            </element>
            <element>
                <object name="ServerObject">
                    <member name="ID">620033</member>
                    <member name="X">19003.61523</member>
                    <member name="Y">-9079.118164</member>
                    <member name="Rotation">-1.570796371</member>
                    <member name="State">0</member>
                    <member name="Actions"/>
                </object>
            </element>
            <element>
                <object name="ServerObject">
                    <member name="ID">620034</member>
                    <member name="X">21981.11523</member>
                    <member name="Y">-6040.196289</member>
                    <member name="Rotation">-1.570796371</member>
                    <member name="State">0</member>
                    <member name="Actions"/>
                </object>
            </element>
            <element>
                <object name="ServerObject">
                    <member name="ID">620035</member>
                    <member name="X">21993.26563</member>
                    <member name="Y">-8953.419922</member>
                    <member name="Rotation">1.570796371</member>
                    <member name="State">1</member>
                    <member name="Actions"/>
                </object>
            </element>
            <element>
                <object name="ServerObject">
                    <member name="ID">620036</member>
                    <member name="X">24995.13867</member>
                    <member name="Y">-6032.810059</member>
                    <member name="Rotation">-1.570796371</member>
                    <member name="State">0</member>
                    <member name="Actions"/>
                </object>
            </element>
            <element>
                <object name="ServerObject">
                    <member name="ID">620037</member>
                    <member name="X">20439.82813</member>
                    <member name="Y">-7516.760742</member>
                    <member name="Rotation">-3.141592741</member>
                    <member name="State">0</member>
                    <member name="Actions"/>
                </object>
            </element>
            <element>
                <object name="ServerObject">
                    <member name="ID">620038</member>
                    <member name="X">23456.27148</member>
                    <member name="Y">-7492.725586</member>
                    <member name="Rotation">-3.141592741</member>
                    <member name="State">0</member>
                    <member name="Actions"/>
                </object>
            </element>
            <element>
                <object name="ServerObject">
                    <member name="ID">620077</member>
                    <member name="X">893.9598389</member>
                    <member name="Y">-8.481764793</member>
                    <member name="Rotation">-0</member>
                    <member name="State">2</member>
                    <member name="Actions"/>
                </object>
            </element>
            <element>
                <object name="ServerObject">
                    <member name="ID">620078</member>
                    <member name="X">13605.73438</member>
                    <member name="Y">493.8392029</member>
                    <member name="Rotation">-0</member>
                    <member name="State">2</member>
                    <member name="Actions"/>
                </object>
            </element>
        </member>
        <member name="Spawns">
            <pair>
                <key>183300001</key>
                <value>
                    <object name="Spawn">
                        <member name="ID">183300001</member>
                        <member name="EnemyType">1833</member>
                        <member name="Drops">
                            <element>
                                <object name="ItemDrop">
                                    <member name="ItemType">40166</member>
                                    <member name="Rate">0.05</member>
                                    <member name="MinStack">1</member>
                                    <member name="MaxStack">1</member>
                                </object>
                            </element>
                            <element>
                                <object name="ItemDrop">
                                    <member name="ItemType">799</member>
                                    <member name="Rate">0.05</member>
                                    <member name="MinStack">198</member>
                                    <member name="MaxStack">238</member>
                                </object>
                            </element>
                            <element>
                                <object name="ItemDrop">
                                    <member name="ItemType">800</member>
                                    <member name="Rate">0.05</member>
                                    <member name="MinStack">148</member>
                                    <member name="MaxStack">180</member>
                                </object>
                            </element>
                            <element>
                                <object name="ItemDrop">
                                    <member name="ItemType">2716</member>
                                    <member name="Rate">0.05</member>
                                    <member name="MinStack">20</member>
                                    <member name="MaxStack">20</member>
                                </object>
                            </element>
                        </member>
                        <!--Max seen: 3-->
                    </object>
                </value>
            </pair>
            <pair>
                <key>183000001</key>
                <value>
                    <object name="Spawn">
                        <member name="ID">183000001</member>
                        <member name="EnemyType">1830</member>
                        <member name="Drops">
                            <element>
                                <object name="ItemDrop">
                                    <member name="ItemType">799</member>
                                    <member name="Rate">0.05</member>
                                    <member name="MinStack">1477</member>
                                    <member name="MaxStack">1477</member>
                                </object>
                            </element>
                            <element>
                                <object name="ItemDrop">
                                    <member name="ItemType">800</member>
                                    <member name="Rate">0.05</member>
                                    <member name="MinStack">951</member>
                                    <member name="MaxStack">951</member>
                                </object>
                            </element>
                        </member>
                        <!--Max seen: 1-->
                    </object>
                </value>
            </pair>
            <pair>
                <key>22200001</key>
                <value>
                    <object name="Spawn">
                        <member name="ID">22200001</member>
                        <member name="EnemyType">222</member>
                        <member name="Drops">
                            <element>
                                <object name="ItemDrop">
                                    <member name="ItemType">800</member>
                                    <member name="Rate">0.05</member>
                                    <member name="MinStack">191</member>
                                    <member name="MaxStack">215</member>
                                </object>
                            </element>
                            <element>
                                <object name="ItemDrop">
                                    <member name="ItemType">799</member>
                                    <member name="Rate">0.05</member>
                                    <member name="MinStack">369</member>
                                    <member name="MaxStack">428</member>
                                </object>
                            </element>
                            <element>
                                <object name="ItemDrop">
                                    <member name="ItemType">2716</member>
                                    <member name="Rate">0.05</member>
                                    <member name="MinStack">20</member>
                                    <member name="MaxStack">20</member>
                                </object>
                            </element>
                            <element>
                                <object name="ItemDrop">
                                    <member name="ItemType">40169</member>
                                    <member name="Rate">0.05</member>
                                    <member name="MinStack">1</member>
                                    <member name="MaxStack">1</member>
                                </object>
                            </element>
                        </member>
                        <!--Max seen: 2-->
                    </object>
                </value>
            </pair>
            <pair>
                <key>182400001</key>
                <value>
                    <object name="Spawn">
                        <member name="ID">182400001</member>
                        <member name="EnemyType">1824</member>
                        <member name="Drops">
                            <element>
                                <object name="ItemDrop">
                                    <member name="ItemType">799</member>
                                    <member name="Rate">0.05</member>
                                    <member name="MinStack">327</member>
                                    <member name="MaxStack">386</member>
                                </object>
                            </element>
                            <element>
                                <object name="ItemDrop">
                                    <member name="ItemType">800</member>
                                    <member name="Rate">0.05</member>
                                    <member name="MinStack">164</member>
                                    <member name="MaxStack">194</member>
                                </object>
                            </element>
                            <element>
                                <object name="ItemDrop">
                                    <member name="ItemType">40169</member>
                                    <member name="Rate">0.05</member>
                                    <member name="MinStack">1</member>
                                    <member name="MaxStack">1</member>
                                </object>
                            </element>
                            <element>
                                <object name="ItemDrop">
                                    <member name="ItemType">2716</member>
                                    <member name="Rate">0.05</member>
                                    <member name="MinStack">20</member>
                                    <member name="MaxStack">20</member>
                                </object>
                            </element>
                            <element>
                                <object name="ItemDrop">
                                    <member name="ItemType">5620</member>
                                    <member name="Rate">0.05</member>
                                    <member name="MinStack">1</member>
                                    <member name="MaxStack">1</member>
                                </object>
                            </element>
                        </member>
                        <!--Max seen: 5-->
                    </object>
                </value>
            </pair>
            <pair>
                <key>183100001</key>
                <value>
                    <object name="Spawn">
                        <member name="ID">183100001</member>
                        <member name="EnemyType">1831</member>
                        <member name="Drops">
                            <element>
                                <object name="ItemDrop">
                                    <member name="ItemType">800</member>
                                    <member name="Rate">0.05</member>
                                    <member name="MinStack">182</member>
                                    <member name="MaxStack">182</member>
                                </object>
                            </element>
                        </member>
                        <!--Max seen: 1-->
                    </object>
                </value>
            </pair>
            <pair>
                <key>183200001</key>
                <value>
                    <object name="Spawn">
                        <member name="ID">183200001</member>
                        <member name="EnemyType">1832</member>
                        <member name="Drops">
                            <element>
                                <object name="ItemDrop">
                                    <member name="ItemType">40166</member>
                                    <member name="Rate">0.05</member>
                                    <member name="MinStack">1</member>
                                    <member name="MaxStack">1</member>
                                </object>
                            </element>
                            <element>
                                <object name="ItemDrop">
                                    <member name="ItemType">799</member>
                                    <member name="Rate">0.05</member>
                                    <member name="MinStack">164</member>
                                    <member name="MaxStack">197</member>
                                </object>
                            </element>
                            <element>
                                <object name="ItemDrop">
                                    <member name="ItemType">800</member>
                                    <member name="Rate">0.05</member>
                                    <member name="MinStack">121</member>
                                    <member name="MaxStack">148</member>
                                </object>
                            </element>
                            <element>
                                <object name="ItemDrop">
                                    <member name="ItemType">2716</member>
                                    <member name="Rate">0.05</member>
                                    <member name="MinStack">20</member>
                                    <member name="MaxStack">20</member>
                                </object>
                            </element>
                        </member>
                        <!--Max seen: 5-->
                    </object>
                </value>
            </pair>
        </member>
        <member name="SpawnGroups">
            <pair>
                <key>1</key>
                <value>
                    <object name="SpawnGroup">
                        <member name="ID">1</member>
                        <member name="SubGroups">
                            <element>182400001</element>
                            <element>183300001</element>
                        </member>
                        <member name="SpawnLocationGroupID">1</member>
                    </object>
                </value>
            </pair>
            <pair>
                <key>2</key>
                <value>
                    <object name="SpawnGroup">
                        <member name="ID">2</member>
                        <member name="SubGroups">
                            <element>182400001</element>
                            <element>183200001</element>
                        </member>
                        <member name="SpawnLocationGroupID">1</member>
                    </object>
                </value>
            </pair>
            <pair>
                <key>3</key>
                <value>
                    <object name="SpawnGroup">
                        <member name="ID">3</member>
                        <member name="SubGroups">
                            <element>183300002</element>
                        </member>
                        <member name="SpawnLocationGroupID">2</member>
                    </object>
                </value>
            </pair>
            <pair>
                <key>4</key>
                <value>
                    <object name="SpawnGroup">
                        <member name="ID">4</member>
                        <member name="SubGroups">
                            <element>182400001</element>
                            <element>183300001</element>
                        </member>
                        <member name="SpawnLocationGroupID">2</member>
                    </object>
                </value>
            </pair>
            <pair>
                <key>5</key>
                <value>
                    <object name="SpawnGroup">
                        <member name="ID">5</member>
                        <member name="SubGroups">
                            <element>183300002</element>
                        </member>
                        <member name="SpawnLocationGroupID">3</member>
                    </object>
                </value>
            </pair>
            <pair>
                <key>6</key>
                <value>
                    <object name="SpawnGroup">
                        <member name="ID">6</member>
                        <member name="SubGroups">
                            <element>22200001</element>
                            <element>182400001</element>
                        </member>
                        <member name="SpawnLocationGroupID">3</member>
                    </object>
                </value>
            </pair>
            <pair>
                <key>7</key>
                <value>
                    <object name="SpawnGroup">
                        <member name="ID">7</member>
                        <member name="SubGroups">
                            <element>183300002</element>
                        </member>
                        <member name="SpawnLocationGroupID">6</member>
                    </object>
                </value>
            </pair>
            <pair>
                <key>8</key>
                <value>
                    <object name="SpawnGroup">
                        <member name="ID">8</member>
                        <member name="SubGroups">
                            <element>183200002</element>
                        </member>
                        <member name="SpawnLocationGroupID">6</member>
                    </object>
                </value>
            </pair>
            <pair>
                <key>9</key>
                <value>
                    <object name="SpawnGroup">
                        <member name="ID">9</member>
                        <member name="SubGroups">
                            <element>183200002</element>
                        </member>
                        <member name="SpawnLocationGroupID">7</member>
                    </object>
                </value>
            </pair>
            <pair>
                <key>10</key>
                <value>
                    <object name="SpawnGroup">
                        <member name="ID">10</member>
                        <member name="SubGroups">
                            <element>183300001</element>
                        </member>
                        <member name="SpawnLocationGroupID">9</member>
                    </object>
                </value>
            </pair>
            <pair>
                <key>11</key>
                <value>
                    <object name="SpawnGroup">
                        <member name="ID">11</member>
                        <member name="SubGroups">
                            <element>22200001</element>
                            <element>182400001</element>
                        </member>
                        <member name="SpawnLocationGroupID">10</member>
                    </object>
                </value>
            </pair>
            <pair>
                <key>12</key>
                <value>
                    <object name="SpawnGroup">
                        <member name="ID">12</member>
                        <member name="SubGroups">
                            <element>183200002</element>
                        </member>
                        <member name="SpawnLocationGroupID">10</member>
                    </object>
                </value>
            </pair>
            <pair>
                <key>13</key>
                <value>
                    <object name="SpawnGroup">
                        <member name="ID">13</member>
                        <member name="SubGroups">
                            <element>183300002</element>
                        </member>
                        <member name="SpawnLocationGroupID">11</member>
                    </object>
                </value>
            </pair>
            <pair>
                <key>14</key>
                <value>
                    <object name="SpawnGroup">
                        <member name="ID">14</member>
                        <member name="SubGroups">
                            <element>182400001</element>
                            <element>183200001</element>
                        </member>
                        <member name="SpawnLocationGroupID">11</member>
                    </object>
                </value>
            </pair>
            <pair>
                <key>15</key>
                <value>
                    <object name="SpawnGroup">
                        <member name="ID">15</member>
                        <member name="SubGroups">
                            <element>183300002</element>
                        </member>
                        <member name="SpawnLocationGroupID">13</member>
                    </object>
                </value>
            </pair>
            <pair>
                <key>16</key>
                <value>
                    <object name="SpawnGroup">
                        <member name="ID">16</member>
                        <member name="SubGroups">
                            <element>182400001</element>
                            <element>183300001</element>
                        </member>
                        <member name="SpawnLocationGroupID">13</member>
                    </object>
                </value>
            </pair>
            <pair>
                <key>17</key>
                <value>
                    <object name="SpawnGroup">
                        <member name="ID">17</member>
                        <member name="SubGroups">
                            <element>183200001</element>
                        </member>
                        <member name="SpawnLocationGroupID">14</member>
                    </object>
                </value>
            </pair>
            <pair>
                <key>18</key>
                <value>
                    <object name="SpawnGroup">
                        <member name="ID">18</member>
                        <member name="SubGroups">
                            <element>182400001</element>
                            <element>183200001</element>
                        </member>
                        <member name="SpawnLocationGroupID">16</member>
                    </object>
                </value>
            </pair>
            <pair>
                <key>19</key>
                <value>
                    <object name="SpawnGroup">
                        <member name="ID">19</member>
                        <member name="SubGroups">
                            <element>22200001</element>
                            <element>182400001</element>
                        </member>
                        <member name="SpawnLocationGroupID">16</member>
                    </object>
                </value>
            </pair>
            <pair>
                <key>20</key>
                <value>
                    <object name="SpawnGroup">
                        <member name="ID">20</member>
                        <member name="SubGroups">
                            <element>182400001</element>
                            <element>183200001</element>
                        </member>
                        <member name="SpawnLocationGroupID">17</member>
                    </object>
                </value>
            </pair>
            <pair>
                <key>21</key>
                <value>
                    <object name="SpawnGroup">
                        <member name="ID">21</member>
                        <member name="SubGroups">
                            <element>22200001</element>
                            <element>182400001</element>
                        </member>
                        <member name="SpawnLocationGroupID">17</member>
                    </object>
                </value>
            </pair>
            <pair>
                <key>22</key>
                <value>
                    <object name="SpawnGroup">
                        <member name="ID">22</member>
                        <member name="SubGroups">
                            <element>22200001</element>
                        </member>
                        <member name="SpawnLocationGroupID">21</member>
                    </object>
                </value>
            </pair>
            <pair>
                <key>23</key>
                <value>
                    <object name="SpawnGroup">
                        <member name="ID">23</member>
                        <member name="SubGroups">
                            <element>183200002</element>
                        </member>
                        <member name="SpawnLocationGroupID">22</member>
                    </object>
                </value>
            </pair>
            <pair>
                <key>22200001</key>
                <value>
                    <object name="SpawnGroup">
                        <member name="ID">22200001</member>
                        <member name="SpawnID">22200001</member>
                        <member name="MaxCount">1</member>
                    </object>
                </value>
            </pair>
            <pair>
                <key>182400001</key>
                <value>
                    <object name="SpawnGroup">
                        <member name="ID">182400001</member>
                        <member name="SpawnID">182400001</member>
                        <member name="MaxCount">1</member>
                    </object>
                </value>
            </pair>
            <pair>
                <key>183200001</key>
                <value>
                    <object name="SpawnGroup">
                        <member name="ID">183200001</member>
                        <member name="SpawnID">183200001</member>
                        <member name="MaxCount">1</member>
                    </object>
                </value>
            </pair>
            <pair>
                <key>183200002</key>
                <value>
                    <object name="SpawnGroup">
                        <member name="ID">183200002</member>
                        <member name="SpawnID">183200001</member>
                        <member name="MaxCount">2</member>
                    </object>
                </value>
            </pair>
            <pair>
                <key>183300001</key>
                <value>
                    <object name="SpawnGroup">
                        <member name="ID">183300001</member>
                        <member name="SpawnID">183300001</member>
                        <member name="MaxCount">1</member>
                    </object>
                </value>
            </pair>
            <pair>
                <key>183300002</key>
                <value>
                    <object name="SpawnGroup">
                        <member name="ID">183300002</member>
                        <member name="SpawnID">183300001</member>
                        <member name="MaxCount">2</member>
                    </object>
                </value>
            </pair>
        </member>
        <member name="SpawnLocationGroups">
            <pair>
                <key>1</key>
                <value>
                    <object name="SpawnLocationGroup">
                        <member name="ID">1</member>
                        <member name="SpotIDs">
                            <element>1</element>
                        </member>
                    </object>
                </value>
            </pair>
            <pair>
                <key>6</key>
                <value>
                    <object name="SpawnLocationGroup">
                        <member name="ID">6</member>
                        <member name="SpotIDs">
                            <element>6</element>
                        </member>
                    </object>
                </value>
            </pair>
            <pair>
                <key>7</key>
                <value>
                    <object name="SpawnLocationGroup">
                        <member name="ID">7</member>
                        <member name="SpotIDs">
                            <element>7</element>
                        </member>
                    </object>
                </value>
            </pair>
            <pair>
                <key>10</key>
                <value>
                    <object name="SpawnLocationGroup">
                        <member name="ID">10</member>
                        <member name="SpotIDs">
                            <element>10</element>
                        </member>
                    </object>
                </value>
            </pair>
            <pair>
                <key>11</key>
                <value>
                    <object name="SpawnLocationGroup">
                        <member name="ID">11</member>
                        <member name="SpotIDs">
                            <element>11</element>
                        </member>
                    </object>
                </value>
            </pair>
            <pair>
                <key>14</key>
                <value>
                    <object name="SpawnLocationGroup">
                        <member name="ID">14</member>
                        <member name="SpotIDs">
                            <element>14</element>
                        </member>
                    </object>
                </value>
            </pair>
            <pair>
                <key>16</key>
                <value>
                    <object name="SpawnLocationGroup">
                        <member name="ID">16</member>
                        <member name="SpotIDs">
                            <element>16</element>
                        </member>
                    </object>
                </value>
            </pair>
            <pair>
                <key>17</key>
                <value>
                    <object name="SpawnLocationGroup">
                        <member name="ID">17</member>
                        <member name="SpotIDs">
                            <element>17</element>
                        </member>
                    </object>
                </value>
            </pair>
            <pair>
                <key>22</key>
                <value>
                    <object name="SpawnLocationGroup">
                        <member name="ID">22</member>
                        <member name="SpotIDs">
                            <element>22</element>
                        </member>
                    </object>
                </value>
            </pair>
            <pair>
                <key>201</key>
                <value>
                    <!--Unbound-->
                    <object name="SpawnLocationGroup">
                        <member name="ID">201</member>
                        <member name="SpotIDs">
                            <element>201</element>
                        </member>
                    </object>
                </value>
            </pair>
            <pair>
                <key>202</key>
                <value>
                    <!--Unbound-->
                    <object name="SpawnLocationGroup">
                        <member name="ID">202</member>
                        <member name="SpotIDs">
                            <element>202</element>
                        </member>
                    </object>
                </value>
            </pair>
            <pair>
                <key>203</key>
                <value>
                    <!--Unbound-->
                    <object name="SpawnLocationGroup">
                        <member name="ID">203</member>
                        <member name="SpotIDs">
                            <element>203</element>
                        </member>
                    </object>
                </value>
            </pair>
            <pair>
                <key>204</key>
                <value>
                    <!--Unbound-->
                    <object name="SpawnLocationGroup">
                        <member name="ID">204</member>
                        <member name="SpotIDs">
                            <element>204</element>
                        </member>
                    </object>
                </value>
            </pair>
        </member>
        <member name="Spots">
            <pair>
                <key>10000</key>
                <value>
                    <!--Definition Args: 0, 34197, 0, 0-->
                    <object name="ServerZoneSpot">
                        <member name="ID">10000</member>
                        <member name="Actions">
                            <element>
                                <object name="ActionStartEvent">
                                    <member name="eventID">debug_noEvent</member>
                                </object>
                            </element>
                        </member>
                    </object>
                </value>
            </pair>
            <pair>
                <key>10010</key>
                <value>
                    <!--Definition Args: 0, 34193, 0, 0-->
                    <object name="ServerZoneSpot">
                        <member name="ID">10010</member>
                        <member name="Actions">
                            <element>
                                <object name="ActionStartEvent">
                                    <member name="eventID">debug_noEvent</member>
                                </object>
                            </element>
                        </member>
                    </object>
                </value>
            </pair>
            <pair>
                <key>10011</key>
                <value>
                    <!--Definition Args: 0, 34195, 0, 0-->
                    <object name="ServerZoneSpot">
                        <member name="ID">10011</member>
                        <member name="Actions">
                            <element>
                                <object name="ActionStartEvent">
                                    <member name="eventID">debug_noEvent</member>
                                </object>
                            </element>
                        </member>
                    </object>
                </value>
            </pair>
            <pair>
                <key>10050</key>
                <value>
                    <!--Definition Args: 0, 34100, 34100, 0-->
                    <object name="ServerZoneSpot">
                        <member name="ID">10050</member>
                        <member name="Actions">
                            <element>
                                <object name="ActionStartEvent">
                                    <member name="eventID">debug_noEvent</member>
                                </object>
                            </element>
                        </member>
                    </object>
                </value>
            </pair>
            <pair>
                <key>10100</key>
                <value>
                    <!--Definition Args: 0, 34199, 0, 0-->
                    <object name="ServerZoneSpot">
                        <member name="ID">10100</member>
                        <member name="Actions">
                            <element>
                                <object name="ActionStartEvent">
                                    <member name="eventID">debug_noEvent</member>
                                </object>
                            </element>
                        </member>
                    </object>
                </value>
            </pair>
            <pair>
                <key>11000</key>
                <value>
                    <!--Definition Args: 0, 34227, 0, 0-->
                    <object name="ServerZoneSpot">
                        <member name="ID">11000</member>
                        <member name="Actions">
                            <element>
                                <object name="ActionStartEvent">
                                    <member name="eventID">debug_noEvent</member>
                                </object>
                            </element>
                        </member>
                    </object>
                </value>
            </pair>
            <pair>
                <key>11001</key>
                <value>
                    <!--Definition Args: 0, 0, 0, 0-->
                    <object name="ServerZoneSpot">
                        <member name="ID">11001</member>
                        <member name="Actions">
                            <element>
                                <object name="ActionStartEvent">
                                    <member name="eventID">debug_noEvent</member>
                                </object>
                            </element>
                        </member>
                    </object>
                </value>
            </pair>
            <pair>
                <key>11002</key>
                <value>
                    <!--Definition Args: 0, 34227, 0, 0-->
                    <object name="ServerZoneSpot">
                        <member name="ID">11002</member>
                        <member name="Actions">
                            <element>
                                <object name="ActionStartEvent">
                                    <member name="eventID">debug_noEvent</member>
                                </object>
                            </element>
                        </member>
                    </object>
                </value>
            </pair>
            <pair>
                <key>20001</key>
                <value>
                    <!--Definition Args: 201, 1, 34101, 0-->
                    <object name="ServerZoneSpot">
                        <member name="ID">20001</member>
                        <member name="Actions">
                            <element>
                                <object name="ActionSpawn">
                                    <member name="spawnGroupIDs">
                                        <element>1</element>
                                        <element>2</element>
                                    </member>
                                    <member name="conditions">ONE_TIME_RANDOM</member>
                                    <member name="defeatActions">
                                        <element>
                                            <object name="ActionStartEvent">
                                                <member name="eventID">debug_noEvent</member>
                                            </object>
                                        </element>
                                    </member>
                                </object>
                            </element>
                        </member>
                    </object>
                </value>
            </pair>
            <pair>
                <key>20002</key>
                <value>
                    <!--Definition Args: 202, 2, 34102, 0-->
                    <object name="ServerZoneSpot">
                        <member name="ID">20002</member>
                        <member name="Actions">
                            <element>
                                <object name="ActionSpawn">
                                    <member name="spawnGroupIDs">
                                        <element>3</element>
                                        <element>4</element>
                                    </member>
                                    <member name="conditions">ONE_TIME_RANDOM</member>
                                    <member name="defeatActions">
                                        <element>
                                            <object name="ActionStartEvent">
                                                <member name="eventID">debug_noEvent</member>
                                            </object>
                                        </element>
                                    </member>
                                </object>
                            </element>
                        </member>
                    </object>
                </value>
            </pair>
            <pair>
                <key>20003</key>
                <value>
                    <!--Definition Args: 203, 3, 34103, 0-->
                    <object name="ServerZoneSpot">
                        <member name="ID">20003</member>
                        <member name="Actions">
                            <element>
                                <object name="ActionSpawn">
                                    <member name="spawnGroupIDs">
                                        <element>5</element>
                                        <element>6</element>
                                    </member>
                                    <member name="conditions">ONE_TIME_RANDOM</member>
                                    <member name="defeatActions">
                                        <element>
                                            <object name="ActionStartEvent">
                                                <member name="eventID">debug_noEvent</member>
                                            </object>
                                        </element>
                                    </member>
                                </object>
                            </element>
                        </member>
                    </object>
                </value>
            </pair>
            <pair>
                <key>20004</key>
                <value>
                    <!--Definition Args: 204, 4, 34104, 0-->
                    <object name="ServerZoneSpot">
                        <member name="ID">20004</member>
                        <member name="Actions">
                            <element>
                                <object name="ActionSpawn">
                                    <member name="spawnGroupIDs"/>
                                    <member name="conditions">ONE_TIME</member>
                                    <member name="defeatActions">
                                        <element>
                                            <object name="ActionStartEvent">
                                                <member name="eventID">debug_noEvent</member>
                                            </object>
                                        </element>
                                    </member>
                                </object>
                            </element>
                        </member>
                    </object>
                </value>
            </pair>
            <pair>
                <key>20005</key>
                <value>
                    <!--Definition Args: 205, 5, 34105, 0-->
                    <object name="ServerZoneSpot">
                        <member name="ID">20005</member>
                        <member name="Actions">
                            <element>
                                <object name="ActionSpawn">
                                    <member name="spawnGroupIDs"/>
                                    <member name="conditions">ONE_TIME</member>
                                    <member name="defeatActions">
                                        <element>
                                            <object name="ActionStartEvent">
                                                <member name="eventID">debug_noEvent</member>
                                            </object>
                                        </element>
                                    </member>
                                </object>
                            </element>
                        </member>
                    </object>
                </value>
            </pair>
            <pair>
                <key>20006</key>
                <value>
                    <!--Definition Args: 206, 6, 34106, 0-->
                    <object name="ServerZoneSpot">
                        <member name="ID">20006</member>
                        <member name="Actions">
                            <element>
                                <object name="ActionSpawn">
                                    <member name="spawnGroupIDs">
                                        <element>7</element>
                                        <element>8</element>
                                    </member>
                                    <member name="conditions">ONE_TIME_RANDOM</member>
                                    <member name="defeatActions">
                                        <element>
                                            <object name="ActionStartEvent">
                                                <member name="eventID">debug_noEvent</member>
                                            </object>
                                        </element>
                                    </member>
                                </object>
                            </element>
                        </member>
                    </object>
                </value>
            </pair>
            <pair>
                <key>20007</key>
                <value>
                    <!--Definition Args: 207, 7, 34107, 0-->
                    <object name="ServerZoneSpot">
                        <member name="ID">20007</member>
                        <member name="Actions">
                            <element>
                                <object name="ActionSpawn">
                                    <member name="spawnGroupIDs">
                                        <element>9</element>
                                    </member>
                                    <member name="conditions">ONE_TIME_RANDOM</member>
                                    <member name="defeatActions">
                                        <element>
                                            <object name="ActionStartEvent">
                                                <member name="eventID">debug_noEvent</member>
                                            </object>
                                        </element>
                                    </member>
                                </object>
                            </element>
                        </member>
                    </object>
                </value>
            </pair>
            <pair>
                <key>20008</key>
                <value>
                    <!--Definition Args: 208, 8, 34108, 0-->
                    <object name="ServerZoneSpot">
                        <member name="ID">20008</member>
                        <member name="Actions">
                            <element>
                                <object name="ActionSpawn">
                                    <member name="spawnGroupIDs"/>
                                    <member name="conditions">ONE_TIME</member>
                                    <member name="defeatActions">
                                        <element>
                                            <object name="ActionStartEvent">
                                                <member name="eventID">debug_noEvent</member>
                                            </object>
                                        </element>
                                    </member>
                                </object>
                            </element>
                        </member>
                    </object>
                </value>
            </pair>
            <pair>
                <key>20009</key>
                <value>
                    <!--Definition Args: 209, 9, 34109, 0-->
                    <object name="ServerZoneSpot">
                        <member name="ID">20009</member>
                        <member name="Actions">
                            <element>
                                <object name="ActionSpawn">
                                    <member name="spawnGroupIDs">
                                        <element>10</element>
                                    </member>
                                    <member name="conditions">ONE_TIME_RANDOM</member>
                                    <member name="defeatActions">
                                        <element>
                                            <object name="ActionStartEvent">
                                                <member name="eventID">debug_noEvent</member>
                                            </object>
                                        </element>
                                    </member>
                                </object>
                            </element>
                        </member>
                    </object>
                </value>
            </pair>
            <pair>
                <key>20010</key>
                <value>
                    <!--Definition Args: 210, 10, 34110, 0-->
                    <object name="ServerZoneSpot">
                        <member name="ID">20010</member>
                        <member name="Actions">
                            <element>
                                <object name="ActionSpawn">
                                    <member name="spawnGroupIDs">
                                        <element>11</element>
                                        <element>12</element>
                                    </member>
                                    <member name="conditions">ONE_TIME_RANDOM</member>
                                    <member name="defeatActions">
                                        <element>
                                            <object name="ActionStartEvent">
                                                <member name="eventID">debug_noEvent</member>
                                            </object>
                                        </element>
                                    </member>
                                </object>
                            </element>
                        </member>
                    </object>
                </value>
            </pair>
            <pair>
                <key>20011</key>
                <value>
                    <!--Definition Args: 211, 11, 34111, 0-->
                    <object name="ServerZoneSpot">
                        <member name="ID">20011</member>
                        <member name="Actions">
                            <element>
                                <object name="ActionSpawn">
                                    <member name="spawnGroupIDs">
                                        <element>13</element>
                                        <element>14</element>
                                    </member>
                                    <member name="conditions">ONE_TIME_RANDOM</member>
                                    <member name="defeatActions">
                                        <element>
                                            <object name="ActionStartEvent">
                                                <member name="eventID">debug_noEvent</member>
                                            </object>
                                        </element>
                                    </member>
                                </object>
                            </element>
                        </member>
                    </object>
                </value>
            </pair>
            <pair>
                <key>20012</key>
                <value>
                    <!--Definition Args: 212, 12, 34112, 0-->
                    <object name="ServerZoneSpot">
                        <member name="ID">20012</member>
                        <member name="Actions">
                            <element>
                                <object name="ActionSpawn">
                                    <member name="spawnGroupIDs"/>
                                    <member name="conditions">ONE_TIME</member>
                                    <member name="defeatActions">
                                        <element>
                                            <object name="ActionStartEvent">
                                                <member name="eventID">debug_noEvent</member>
                                            </object>
                                        </element>
                                    </member>
                                </object>
                            </element>
                        </member>
                    </object>
                </value>
            </pair>
            <pair>
                <key>20013</key>
                <value>
                    <!--Definition Args: 213, 13, 34113, 0-->
                    <object name="ServerZoneSpot">
                        <member name="ID">20013</member>
                        <member name="Actions">
                            <element>
                                <object name="ActionSpawn">
                                    <member name="spawnGroupIDs">
                                        <element>15</element>
                                        <element>16</element>
                                    </member>
                                    <member name="conditions">ONE_TIME_RANDOM</member>
                                    <member name="defeatActions">
                                        <element>
                                            <object name="ActionStartEvent">
                                                <member name="eventID">debug_noEvent</member>
                                            </object>
                                        </element>
                                    </member>
                                </object>
                            </element>
                        </member>
                    </object>
                </value>
            </pair>
            <pair>
                <key>20014</key>
                <value>
                    <!--Definition Args: 214, 14, 34114, 0-->
                    <object name="ServerZoneSpot">
                        <member name="ID">20014</member>
                        <member name="Actions">
                            <element>
                                <object name="ActionSpawn">
                                    <member name="spawnGroupIDs">
                                        <element>17</element>
                                    </member>
                                    <member name="conditions">ONE_TIME_RANDOM</member>
                                    <member name="defeatActions">
                                        <element>
                                            <object name="ActionStartEvent">
                                                <member name="eventID">debug_noEvent</member>
                                            </object>
                                        </element>
                                    </member>
                                </object>
                            </element>
                        </member>
                    </object>
                </value>
            </pair>
            <pair>
                <key>20015</key>
                <value>
                    <!--Definition Args: 215, 15, 34115, 0-->
                    <object name="ServerZoneSpot">
                        <member name="ID">20015</member>
                        <member name="Actions">
                            <element>
                                <object name="ActionSpawn">
                                    <member name="spawnGroupIDs"/>
                                    <member name="conditions">ONE_TIME</member>
                                    <member name="defeatActions">
                                        <element>
                                            <object name="ActionStartEvent">
                                                <member name="eventID">debug_noEvent</member>
                                            </object>
                                        </element>
                                    </member>
                                </object>
                            </element>
                        </member>
                    </object>
                </value>
            </pair>
            <pair>
                <key>20016</key>
                <value>
                    <!--Definition Args: 216, 16, 34116, 0-->
                    <object name="ServerZoneSpot">
                        <member name="ID">20016</member>
                        <member name="Actions">
                            <element>
                                <object name="ActionSpawn">
                                    <member name="spawnGroupIDs">
                                        <element>18</element>
                                        <element>19</element>
                                    </member>
                                    <member name="conditions">ONE_TIME_RANDOM</member>
                                    <member name="defeatActions">
                                        <element>
                                            <object name="ActionStartEvent">
                                                <member name="eventID">debug_noEvent</member>
                                            </object>
                                        </element>
                                    </member>
                                </object>
                            </element>
                        </member>
                    </object>
                </value>
            </pair>
            <pair>
                <key>20017</key>
                <value>
                    <!--Definition Args: 217, 17, 34117, 0-->
                    <object name="ServerZoneSpot">
                        <member name="ID">20017</member>
                        <member name="Actions">
                            <element>
                                <object name="ActionSpawn">
                                    <member name="spawnGroupIDs">
                                        <element>20</element>
                                        <element>21</element>
                                    </member>
                                    <member name="conditions">ONE_TIME_RANDOM</member>
                                    <member name="defeatActions">
                                        <element>
                                            <object name="ActionStartEvent">
                                                <member name="eventID">debug_noEvent</member>
                                            </object>
                                        </element>
                                    </member>
                                </object>
                            </element>
                        </member>
                    </object>
                </value>
            </pair>
            <pair>
                <key>20018</key>
                <value>
                    <!--Definition Args: 218, 18, 34118, 0-->
                    <object name="ServerZoneSpot">
                        <member name="ID">20018</member>
                        <member name="Actions">
                            <element>
                                <object name="ActionSpawn">
                                    <member name="spawnGroupIDs"/>
                                    <member name="conditions">ONE_TIME</member>
                                    <member name="defeatActions">
                                        <element>
                                            <object name="ActionStartEvent">
                                                <member name="eventID">debug_noEvent</member>
                                            </object>
                                        </element>
                                    </member>
                                </object>
                            </element>
                        </member>
                    </object>
                </value>
            </pair>
            <pair>
                <key>20019</key>
                <value>
                    <!--Definition Args: 219, 19, 34119, 0-->
                    <object name="ServerZoneSpot">
                        <member name="ID">20019</member>
                        <member name="Actions">
                            <element>
                                <object name="ActionSpawn">
                                    <member name="spawnGroupIDs"/>
                                    <member name="conditions">ONE_TIME</member>
                                    <member name="defeatActions">
                                        <element>
                                            <object name="ActionStartEvent">
                                                <member name="eventID">debug_noEvent</member>
                                            </object>
                                        </element>
                                    </member>
                                </object>
                            </element>
                        </member>
                    </object>
                </value>
            </pair>
            <pair>
                <key>20020</key>
                <value>
                    <!--Definition Args: 220, 20, 34120, 0-->
                    <object name="ServerZoneSpot">
                        <member name="ID">20020</member>
                        <member name="Actions">
                            <element>
                                <object name="ActionSpawn">
                                    <member name="spawnGroupIDs"/>
                                    <member name="conditions">ONE_TIME</member>
                                    <member name="defeatActions">
                                        <element>
                                            <object name="ActionStartEvent">
                                                <member name="eventID">debug_noEvent</member>
                                            </object>
                                        </element>
                                    </member>
                                </object>
                            </element>
                        </member>
                    </object>
                </value>
            </pair>
            <pair>
                <key>20021</key>
                <value>
                    <!--Definition Args: 221, 21, 34121, 0-->
                    <object name="ServerZoneSpot">
                        <member name="ID">20021</member>
                        <member name="Actions">
                            <element>
                                <object name="ActionSpawn">
                                    <member name="spawnGroupIDs">
                                        <element>22</element>
                                    </member>
                                    <member name="conditions">ONE_TIME_RANDOM</member>
                                    <member name="defeatActions">
                                        <element>
                                            <object name="ActionStartEvent">
                                                <member name="eventID">debug_noEvent</member>
                                            </object>
                                        </element>
                                    </member>
                                </object>
                            </element>
                        </member>
                    </object>
                </value>
            </pair>
            <pair>
                <key>20022</key>
                <value>
                    <!--Definition Args: 222, 22, 34122, 0-->
                    <object name="ServerZoneSpot">
                        <member name="ID">20022</member>
                        <member name="Actions">
                            <element>
                                <object name="ActionSpawn">
                                    <member name="spawnGroupIDs">
                                        <element>23</element>
                                    </member>
                                    <member name="conditions">ONE_TIME_RANDOM</member>
                                    <member name="defeatActions">
                                        <element>
                                            <object name="ActionStartEvent">
                                                <member name="eventID">debug_noEvent</member>
                                            </object>
                                        </element>
                                    </member>
                                </object>
                            </element>
                        </member>
                    </object>
                </value>
            </pair>
            <pair>
                <key>30011</key>
                <value>
                    <object name="ServerZoneSpot">
                        <member name="ID">30011</member>
                        <member name="Actions">
                            <element>
                                <object name="ActionSetNPCState">
                                    <member name="actorID">620029</member>
                                    <member name="state">3</member>
                                </object>
                            </element>
                        </member>
                    </object>
                </value>
            </pair>
            <pair>
                <key>30012</key>
                <value>
                    <object name="ServerZoneSpot">
                        <member name="ID">30012</member>
                        <member name="Actions">
                            <element>
                                <object name="ActionSetNPCState">
                                    <member name="actorID">620022</member>
                                    <member name="state">3</member>
                                </object>
                            </element>
                        </member>
                    </object>
                </value>
            </pair>
            <pair>
                <key>30020</key>
                <value>
                    <object name="ServerZoneSpot">
                        <member name="ID">30020</member>
                        <member name="Actions">
                            <element>
                                <object name="ActionSetNPCState">
                                    <member name="actorID">620031</member>
                                    <member name="state">3</member>
                                </object>
                            </element>
                        </member>
                    </object>
                </value>
            </pair>
            <pair>
                <key>30028</key>
                <value>
                    <object name="ServerZoneSpot">
                        <member name="ID">30028</member>
                        <member name="Actions">
                            <element>
                                <object name="ActionSetNPCState">
                                    <member name="actorID">620030</member>
                                    <member name="state">3</member>
                                </object>
                            </element>
                        </member>
                    </object>
                </value>
            </pair>
            <pair>
                <!-- Spot data generated -->
                <key>40000</key>
                <value>
                    <object name="ServerZoneSpot">
                        <member name="ID">40000</member>
                        <member name="Actions">
                            <element>
                                <object name="ActionZoneChange">
                                    <member name="zoneID">620103</member>
                                    <member name="spotID">50001</member>
                                </object>
                            </element>
                        </member>
                    </object>
                </value>
            </pair>
            <pair>
                <!-- Spot data generated -->
                <key>40001</key>
                <value>
                    <object name="ServerZoneSpot">
                        <member name="ID">40001</member>
                        <member name="Actions">
                            <element>
                                <object name="ActionZoneChange">
                                    <member name="zoneID">620106</member>
                                    <member name="spotID">50000</member>
                                </object>
                            </element>
                        </member>
                    </object>
                </value>
            </pair>
        </member>
        <member name="SetupActions"/>
    </object>
</objects>